py_excel_form_extractor-0.3.41.dist-info/WHEEL
py_excel_form_extractor-0.3.41.dist-info/top_level.txt
py_excel_form_extractor-0.3.41.dist-info/METADATA
py_excel_form_extractor-0.3.41.dist-info/RECORD
py_excel_form_extractor-0.3.41.dist-info/licenses/LICENSE
py_excel_form_extractor/extractor.c
py_excel_form_extractor/go.py
py_excel_form_extractor/utils.py
py_excel_form_extractor/extractor_go.h
py_excel_form_extractor/extractor.py
py_excel_form_extractor/extractor.go
py_excel_form_extractor/build.py
py_excel_form_extractor/_extractor.cpython-312-aarch64-linux-gnu.so
py_excel_form_extractor/__init__.py
py_excel_form_extractor/_extractor.cpython-312-aarch64-linux-gnu.h
