Metadata-Version: 2.4
Name: py-excel-form-extractor
Version: 0.3.41
Summary: Extract excel form content into structured data
Home-page: https://github.com/adhadse/excelFormExtractor
Author: Anurag Dhadse
Author-email: Anurag Dhadse <hello@adhadse.com>
License: MIT
Keywords: go,golang,python,excel,xlsx,form,extractor
Classifier: Programming Language :: Python :: 3
Classifier: License :: OSI Approved :: MIT License
Requires-Python: >=3.8
License-File: LICENSE
Dynamic: author
Dynamic: home-page
Dynamic: keywords
Dynamic: license-file
